ta_pack/__init__.py
ta_pack/average_true_range.py
ta_pack/exponential_moving_average.py
ta_pack/simple_moving_average.py
ta_pack-0.2.dist-info/LICENSE.txt
ta_pack-0.2.dist-info/METADATA
ta_pack-0.2.dist-info/WHEEL
ta_pack-0.2.dist-info/top_level.txt
ta_pack-0.2.dist-info/RECORD
