Metadata-Version: 2.1
Name: ta-pack
Version: 0.2
Summary: This is a sample package for technical analysis library.
Home-page: UNKNOWN
Author: Zahid Ahmed
Author-email: zahid023045@gmail.com
License: UNKNOWN
Platform: UNKNOWN
Classifier: Programming Language :: Python :: 3
Classifier: License :: OSI Approved :: MIT License
Classifier: Operating System :: OS Independent
